<?xml version="1.0" encoding="UTF-8"?>
<GenRun Id="impl_1" LaunchPart="xc7a35tfgg484-2" LaunchTime="1691222982">
  <File Type="ROUTE-PWR" Name="TOP_new_power_routed.rpt"/>
  <File Type="PA-TCL" Name="TOP_new.tcl"/>
  <File Type="ROUTE-PWR-SUM" Name="TOP_new_power_summary_routed.pb"/>
  <File Type="REPORTS-TCL" Name="TOP_new_reports.tcl"/>
  <File Type="BITSTR-MSK" Name="TOP_new.msk"/>
  <File Type="ROUTE-CLK" Name="TOP_new_clock_utilization_routed.rpt"/>
  <File Type="RDI-RDI" Name="TOP_new.vdi"/>
  <File Type="BG-BIT" Name="TOP_new.bit"/>
  <File Type="BG-DRC" Name="TOP_new.drc"/>
  <File Type="BG-BGN" Name="TOP_new.bgn"/>
  <File Type="BG-BIN" Name="TOP_new.bin"/>
  <File Type="BITSTR-RBT" Name="TOP_new.rbt"/>
  <File Type="BITSTR-NKY" Name="TOP_new.nky"/>
  <File Type="BITSTR-BMM" Name="TOP_new_bd.bmm"/>
  <File Type="BITSTR-MMI" Name="TOP_new.mmi"/>
  <File Type="ROUTE-METHODOLOGY-DRC" Name="TOP_new_methodology_drc_routed.rpt"/>
  <File Type="BITSTR-SYSDEF" Name="TOP_new.sysdef"/>
  <File Type="ROUTE-METHODOLOGY-DRC-PB" Name="TOP_new_methodology_drc_routed.pb"/>
  <File Type="BITSTR-LTX" Name="debug_nets.ltx"/>
  <File Type="BITSTR-LTX" Name="TOP_new.ltx"/>
  <File Type="WBT-USG" Name="usage_statistics_webtalk.html"/>
  <File Type="OPT-DRC" Name="TOP_new_drc_opted.rpt"/>
  <File Type="OPT-HWDEF" Name="TOP_new.hwdef"/>
  <File Type="PLACE-IO" Name="TOP_new_io_placed.rpt"/>
  <File Type="PLACE-UTIL" Name="TOP_new_utilization_placed.rpt"/>
  <File Type="PLACE-UTIL-PB" Name="TOP_new_utilization_placed.pb"/>
  <File Type="PLACE-CTRL" Name="TOP_new_control_sets_placed.rpt"/>
  <File Type="PLACE-PRE-SIMILARITY" Name="TOP_new_incremental_reuse_pre_placed.rpt"/>
  <File Type="ROUTE-DRC" Name="TOP_new_drc_routed.rpt"/>
  <File Type="ROUTE-DRC-PB" Name="TOP_new_drc_routed.pb"/>
  <File Type="ROUTE-PWR-RPX" Name="TOP_new_power_routed.rpx"/>
  <File Type="ROUTE-STATUS" Name="TOP_new_route_status.rpt"/>
  <File Type="ROUTE-STATUS-PB" Name="TOP_new_route_status.pb"/>
  <File Type="ROUTE-DCP" Name="TOP_new_routed.dcp"/>
  <File Type="ROUTE-ERROR-DCP" Name="TOP_new_routed_error.dcp"/>
  <File Type="ROUTE-BLACKBOX-DCP" Name="TOP_new_routed_bb.dcp"/>
  <File Type="ROUTE-TIMINGSUMMARY" Name="TOP_new_timing_summary_routed.rpt"/>
  <File Type="ROUTE-TIMING-PB" Name="TOP_new_timing_summary_routed.pb"/>
  <File Type="ROUTE-TIMING-RPX" Name="TOP_new_timing_summary_routed.rpx"/>
  <File Type="ROUTE-BUS-SKEW" Name="TOP_new_bus_skew_routed.rpt"/>
  <File Type="ROUTE-BUS-SKEW-PB" Name="TOP_new_bus_skew_routed.pb"/>
  <File Type="ROUTE-BUS-SKEW-RPX" Name="TOP_new_bus_skew_routed.rpx"/>
  <File Type="OPT-DCP" Name="TOP_new_opt.dcp"/>
  <File Type="PLACE-DCP" Name="TOP_new_placed.dcp"/>
  <File Type="PWROPT-DCP" Name="TOP_new_pwropt.dcp"/>
  <File Type="POSTPLACE-PWROPT-DCP" Name="TOP_new_postplace_pwropt.dcp"/>
  <File Type="PHYSOPT-DCP" Name="TOP_new_physopt.dcp"/>
  <File Type="POSTROUTE-PHYSOPT-DCP" Name="TOP_new_postroute_physopt.dcp"/>
  <File Type="POSTROUTE-PHYSOPT-BLACKBOX-DCP" Name="TOP_new_postroute_physopt_bb.dcp"/>
  <File Type="ROUTE-DRC-RPX" Name="TOP_new_drc_routed.rpx"/>
  <File Type="ROUTE-METHODOLOGY-DRC-RPX" Name="TOP_new_methodology_drc_routed.rpx"/>
  <File Type="PDI-FILE" Name="TOP_new.pdi"/>
  <File Type="RCFI_FILE" Name="TOP_new.rcfi"/>
  <File Type="CFI_FILE" Name="TOP_new.cfi"/>
  <File Type="RNPI_FILE" Name="TOP_new.rnpi"/>
  <File Type="NPI_FILE" Name="TOP_new.npi"/>
  <File Type="RBD_FILE" Name="TOP_new.rbd"/>
  <FileSet Name="sources" Type="DesignSrcs" RelSrcDir="$PSRCDIR/sources_1">
    <Filter Type="Srcs"/>
    <File Path="$PPRDIR/../src/TOP.v">
      <FileInfo>
        <Attr Name="UserDisabled" Val="1"/>
        <Attr Name="UsedIn" Val="synthesis"/>
        <Attr Name="UsedIn" Val="implementation"/>
        <Attr Name="UsedIn" Val="simulation"/>
      </FileInfo>
    </File>
    <File Path="$PPRDIR/../src/two_channel_ADC.v">
      <FileInfo>
        <Attr Name="UsedIn" Val="synthesis"/>
        <Attr Name="UsedIn" Val="implementation"/>
        <Attr Name="UsedIn" Val="simulation"/>
      </FileInfo>
    </File>
    <File Path="$PPRDIR/../src/filter/CIC_decimation_10_fs6MHz.v">
      <FileInfo>
        <Attr Name="UsedIn" Val="synthesis"/>
        <Attr Name="UsedIn" Val="implementation"/>
        <Attr Name="UsedIn" Val="simulation"/>
      </FileInfo>
    </File>
    <File Path="$PPRDIR/../../../Matlab/COE/AM_I.coe">
      <FileInfo>
        <Attr Name="UsedIn" Val="synthesis"/>
        <Attr Name="UsedIn" Val="simulation"/>
      </FileInfo>
    </File>
    <File Path="$PPRDIR/../../../Matlab/COE/AM_Q.coe">
      <FileInfo>
        <Attr Name="UsedIn" Val="synthesis"/>
        <Attr Name="UsedIn" Val="simulation"/>
      </FileInfo>
    </File>
    <File Path="$PPRDIR/../../../Matlab/COE/FM_I.coe">
      <FileInfo>
        <Attr Name="UsedIn" Val="synthesis"/>
        <Attr Name="UsedIn" Val="simulation"/>
      </FileInfo>
    </File>
    <File Path="$PPRDIR/../../../Matlab/COE/FM_Q.coe">
      <FileInfo>
        <Attr Name="UsedIn" Val="synthesis"/>
        <Attr Name="UsedIn" Val="simulation"/>
      </FileInfo>
    </File>
    <File Path="$PPRDIR/../../../Matlab/COE/calibrate_I.coe">
      <FileInfo>
        <Attr Name="UsedIn" Val="synthesis"/>
        <Attr Name="UsedIn" Val="simulation"/>
      </FileInfo>
    </File>
    <File Path="$PPRDIR/../../../Matlab/COE/calibrate_Q.coe">
      <FileInfo>
        <Attr Name="UsedIn" Val="synthesis"/>
        <Attr Name="UsedIn" Val="simulation"/>
      </FileInfo>
    </File>
    <File Path="$PPRDIR/../../../Matlab/COE/2FSK_I.coe">
      <FileInfo>
        <Attr Name="UsedIn" Val="synthesis"/>
        <Attr Name="UsedIn" Val="simulation"/>
      </FileInfo>
    </File>
    <File Path="$PPRDIR/../../../Matlab/COE/2FSK_Q.coe">
      <FileInfo>
        <Attr Name="UsedIn" Val="synthesis"/>
        <Attr Name="UsedIn" Val="simulation"/>
      </FileInfo>
    </File>
    <File Path="$PPRDIR/../../../Matlab/COE/2PSK_I.coe">
      <FileInfo>
        <Attr Name="UsedIn" Val="synthesis"/>
        <Attr Name="UsedIn" Val="simulation"/>
      </FileInfo>
    </File>
    <File Path="$PPRDIR/../../../Matlab/COE/2PSK_Q.coe">
      <FileInfo>
        <Attr Name="UsedIn" Val="synthesis"/>
        <Attr Name="UsedIn" Val="simulation"/>
      </FileInfo>
    </File>
    <File Path="$PSRCDIR/sources_1/ip/dist_mem_gen_Q/dist_mem_gen_Q.xci">
      <FileInfo>
        <Attr Name="UsedIn" Val="synthesis"/>
        <Attr Name="UsedIn" Val="implementation"/>
        <Attr Name="UsedIn" Val="simulation"/>
      </FileInfo>
    </File>
    <File Path="$PSRCDIR/sources_1/new/TOP_new.v">
      <FileInfo>
        <Attr Name="UsedIn" Val="synthesis"/>
        <Attr Name="UsedIn" Val="implementation"/>
        <Attr Name="UsedIn" Val="simulation"/>
      </FileInfo>
    </File>
    <File Path="$PPRDIR/../src/filter/CIC_decimation_20_fs36MHz.v">
      <FileInfo>
        <Attr Name="UsedIn" Val="synthesis"/>
        <Attr Name="UsedIn" Val="implementation"/>
        <Attr Name="UsedIn" Val="simulation"/>
      </FileInfo>
    </File>
    <File Path="$PPRDIR/../../../../2019_G/Vivado/FM_audio_demodulate/src/two_channel_dac.v">
      <FileInfo>
        <Attr Name="UsedIn" Val="synthesis"/>
        <Attr Name="UsedIn" Val="implementation"/>
        <Attr Name="UsedIn" Val="simulation"/>
      </FileInfo>
    </File>
    <File Path="$PPRDIR/../src/cal/Phase_dev_cal.v">
      <FileInfo>
        <Attr Name="UsedIn" Val="synthesis"/>
        <Attr Name="UsedIn" Val="implementation"/>
        <Attr Name="UsedIn" Val="simulation"/>
      </FileInfo>
    </File>
    <File Path="$PPRDIR/../src/demod/Demodulate.v">
      <FileInfo>
        <Attr Name="UsedIn" Val="synthesis"/>
        <Attr Name="UsedIn" Val="implementation"/>
        <Attr Name="UsedIn" Val="simulation"/>
      </FileInfo>
    </File>
    <File Path="$PPRDIR/../src/demod/Cordic.v">
      <FileInfo>
        <Attr Name="UsedIn" Val="synthesis"/>
        <Attr Name="UsedIn" Val="implementation"/>
        <Attr Name="UsedIn" Val="simulation"/>
      </FileInfo>
    </File>
    <File Path="$PPRDIR/../src/demod/IQ_generate.v">
      <FileInfo>
        <Attr Name="UsedIn" Val="synthesis"/>
        <Attr Name="UsedIn" Val="implementation"/>
        <Attr Name="UsedIn" Val="simulation"/>
      </FileInfo>
    </File>
    <File Path="$PPRDIR/../../../Matlab/COE/phase.coe">
      <FileInfo>
        <Attr Name="UsedIn" Val="synthesis"/>
        <Attr Name="UsedIn" Val="simulation"/>
      </FileInfo>
    </File>
    <File Path="$PPRDIR/../src/filter/LPF_60k_fs1_8MHz.v">
      <FileInfo>
        <Attr Name="UsedIn" Val="synthesis"/>
        <Attr Name="UsedIn" Val="implementation"/>
        <Attr Name="UsedIn" Val="simulation"/>
      </FileInfo>
    </File>
    <File Path="$PPRDIR/../src/filter/LPF_20kHz_fs1_8MHz.v">
      <FileInfo>
        <Attr Name="UsedIn" Val="synthesis"/>
        <Attr Name="UsedIn" Val="implementation"/>
        <Attr Name="UsedIn" Val="simulation"/>
      </FileInfo>
    </File>
    <File Path="$PPRDIR/../src/TOP_FSM.v">
      <FileInfo>
        <Attr Name="UsedIn" Val="synthesis"/>
        <Attr Name="UsedIn" Val="implementation"/>
        <Attr Name="UsedIn" Val="simulation"/>
      </FileInfo>
    </File>
    <File Path="$PPRDIR/../src/cal/Max_Min.v">
      <FileInfo>
        <Attr Name="UsedIn" Val="synthesis"/>
        <Attr Name="UsedIn" Val="implementation"/>
        <Attr Name="UsedIn" Val="simulation"/>
      </FileInfo>
    </File>
    <File Path="$PPRDIR/../src/cal/Get_Ma.v">
      <FileInfo>
        <Attr Name="UsedIn" Val="synthesis"/>
        <Attr Name="UsedIn" Val="implementation"/>
        <Attr Name="UsedIn" Val="simulation"/>
      </FileInfo>
    </File>
    <File Path="$PPRDIR/../src/cal/FSM_Max_Min.v">
      <FileInfo>
        <Attr Name="UsedIn" Val="synthesis"/>
        <Attr Name="UsedIn" Val="implementation"/>
        <Attr Name="UsedIn" Val="simulation"/>
      </FileInfo>
    </File>
    <File Path="$PPRDIR/../src/Judge_and_calculate.v">
      <FileInfo>
        <Attr Name="UsedIn" Val="synthesis"/>
        <Attr Name="UsedIn" Val="implementation"/>
        <Attr Name="UsedIn" Val="simulation"/>
      </FileInfo>
    </File>
    <File Path="$PPRDIR/../src/cal/SquareJudge.v">
      <FileInfo>
        <Attr Name="UsedIn" Val="synthesis"/>
        <Attr Name="UsedIn" Val="implementation"/>
        <Attr Name="UsedIn" Val="simulation"/>
      </FileInfo>
    </File>
    <File Path="$PPRDIR/../src/cal/Signal_discrim.v">
      <FileInfo>
        <Attr Name="UsedIn" Val="synthesis"/>
        <Attr Name="UsedIn" Val="implementation"/>
        <Attr Name="UsedIn" Val="simulation"/>
      </FileInfo>
    </File>
    <File Path="$PPRDIR/../src/DAC_selector.v">
      <FileInfo>
        <Attr Name="UsedIn" Val="synthesis"/>
        <Attr Name="UsedIn" Val="implementation"/>
        <Attr Name="UsedIn" Val="simulation"/>
      </FileInfo>
    </File>
    <File Path="$PPRDIR/../src/Message_generator.v">
      <FileInfo>
        <Attr Name="UsedIn" Val="synthesis"/>
        <Attr Name="UsedIn" Val="implementation"/>
        <Attr Name="UsedIn" Val="simulation"/>
      </FileInfo>
    </File>
    <File Path="$PPRDIR/../src/cal/Fre_Judge.v">
      <FileInfo>
        <Attr Name="UsedIn" Val="synthesis"/>
        <Attr Name="UsedIn" Val="implementation"/>
        <Attr Name="UsedIn" Val="simulation"/>
      </FileInfo>
    </File>
    <File Path="$PPRDIR/../src/ASK_decision.v">
      <FileInfo>
        <Attr Name="UsedIn" Val="synthesis"/>
        <Attr Name="UsedIn" Val="implementation"/>
        <Attr Name="UsedIn" Val="simulation"/>
      </FileInfo>
    </File>
    <File Path="$PPRDIR/../src/AGC.v">
      <FileInfo>
        <Attr Name="UsedIn" Val="synthesis"/>
        <Attr Name="UsedIn" Val="implementation"/>
        <Attr Name="UsedIn" Val="simulation"/>
      </FileInfo>
    </File>
    <File Path="$PPRDIR/../src/cal/Find_Max_Lim.v">
      <FileInfo>
        <Attr Name="UsedIn" Val="synthesis"/>
        <Attr Name="UsedIn" Val="implementation"/>
        <Attr Name="UsedIn" Val="simulation"/>
      </FileInfo>
    </File>
    <File Path="$PPRDIR/../src/AM_DC_Isolator.v">
      <FileInfo>
        <Attr Name="UsedIn" Val="synthesis"/>
        <Attr Name="UsedIn" Val="implementation"/>
        <Attr Name="UsedIn" Val="simulation"/>
      </FileInfo>
    </File>
    <File Path="$PPRDIR/../src/Communicate.v">
      <FileInfo>
        <Attr Name="UsedIn" Val="synthesis"/>
        <Attr Name="UsedIn" Val="implementation"/>
        <Attr Name="UsedIn" Val="simulation"/>
      </FileInfo>
    </File>
    <File Path="$PPRDIR/../src/PSK_Judge.v">
      <FileInfo>
        <Attr Name="UsedIn" Val="synthesis"/>
        <Attr Name="UsedIn" Val="implementation"/>
        <Attr Name="UsedIn" Val="simulation"/>
      </FileInfo>
    </File>
    <Config>
      <Option Name="DesignMode" Val="RTL"/>
      <Option Name="TopModule" Val="TOP_new"/>
    </Config>
  </FileSet>
  <FileSet Name="constrs_in" Type="Constrs" RelSrcDir="$PSRCDIR/constrs_1">
    <Filter Type="Constrs"/>
    <File Path="$PPRDIR/../constraints/D2023.xdc">
      <FileInfo>
        <Attr Name="UsedIn" Val="synthesis"/>
        <Attr Name="UsedIn" Val="implementation"/>
      </FileInfo>
    </File>
    <File Path="$PSRCDIR/constrs_1/new/TOP_new.xdc">
      <FileInfo>
        <Attr Name="UsedIn" Val="synthesis"/>
        <Attr Name="UsedIn" Val="implementation"/>
      </FileInfo>
    </File>
    <Config>
      <Option Name="TargetConstrsFile" Val="$PSRCDIR/constrs_1/new/TOP_new.xdc"/>
      <Option Name="ConstrsType" Val="XDC"/>
    </Config>
  </FileSet>
  <FileSet Name="utils" Type="Utils" RelSrcDir="$PSRCDIR/utils_1">
    <Filter Type="Utils"/>
    <Config>
      <Option Name="TopAutoSet" Val="TRUE"/>
    </Config>
  </FileSet>
  <Strategy Version="1" Minor="2">
    <StratHandle Name="Vivado Implementation Defaults" Flow="Vivado Implementation 2019"/>
    <Step Id="init_design"/>
    <Step Id="opt_design"/>
    <Step Id="power_opt_design"/>
    <Step Id="place_design"/>
    <Step Id="post_place_power_opt_design"/>
    <Step Id="phys_opt_design" EnableStepBool="1"/>
    <Step Id="route_design"/>
    <Step Id="post_route_phys_opt_design"/>
    <Step Id="write_bitstream"/>
    <Step Id="write_device_image"/>
  </Strategy>
  <BlockFileSet Type="BlockSrcs" Name="clk_wiz_0"/>
  <BlockFileSet Type="BlockSrcs" Name="dist_mem_gen_I"/>
  <BlockFileSet Type="BlockSrcs" Name="ila_0"/>
  <BlockFileSet Type="BlockSrcs" Name="mult_gen_0"/>
  <BlockFileSet Type="BlockSrcs" Name="dist_mem_ph"/>
  <BlockFileSet Type="BlockSrcs" Name="ila_1"/>
</GenRun>
